aws_toolkits/__init__.py
aws_toolkits/ec2manager/__init__.py
aws_toolkits/ec2manager/ec2_manager.py
aws_toolkits/ec2manager/security_group_mgr.py
aws_toolkits/glacier/__init__.py
aws_toolkits/glacier/glacier.py
aws_toolkits-1.0.3.dist-info/licenses/LICENSE
aws_toolkits-1.0.3.dist-info/METADATA
aws_toolkits-1.0.3.dist-info/WHEEL
aws_toolkits-1.0.3.dist-info/entry_points.txt
aws_toolkits-1.0.3.dist-info/top_level.txt
aws_toolkits-1.0.3.dist-info/RECORD
