Metadata-Version: 2.4
Name: aws_toolkits
Version: 1.0.3
Summary: A toolbox for AWS services
Author-email: YQ Tsui <qianyun210603@hotmail.com>
License: MIT
Classifier: Development Status :: 2 - Pre-Alpha
Classifier: Operating System :: OS Independent
Classifier: Programming Language :: Python :: 3
Classifier: Programming Language :: Python :: 3.10
Classifier: Programming Language :: Python :: 3.11
Classifier: Programming Language :: Python :: 3.12
Classifier: Topic :: System :: Systems Administration
Classifier: Programming Language :: Python :: Implementation :: CPython
Classifier: License :: OSI Approved :: MIT License
License-File: LICENSE
Requires-Dist: boto3
Requires-Dist: loguru
Requires-Dist: pandas
Provides-Extra: glacier
Requires-Dist: tabulate; extra == "glacier"
Requires-Dist: tqdm; extra == "glacier"
Provides-Extra: ec2manager
Requires-Dist: PySide6; extra == "ec2manager"
Requires-Dist: requests; extra == "ec2manager"
Requires-Dist: ruamel.yaml; extra == "ec2manager"
Provides-Extra: dev
Requires-Dist: setuptools; extra == "dev"
Requires-Dist: setuptools_scm; extra == "dev"
Requires-Dist: wheel; extra == "dev"
Requires-Dist: build; extra == "dev"
Requires-Dist: black; extra == "dev"
Requires-Dist: isort; extra == "dev"
Requires-Dist: pylint; extra == "dev"
Dynamic: license-file
